MANIFEST.in
README.md
requirements.txt
setup.cfg
setup.py
bin/whale-linter
whale_linter.egg-info/PKG-INFO
whale_linter.egg-info/SOURCES.txt
whale_linter.egg-info/dependency_links.txt
whale_linter.egg-info/not-zip-safe
whale_linter.egg-info/requires.txt
whale_linter.egg-info/top_level.txt
whalelinter/__init__.py
whalelinter/app.py
whalelinter/checker.py
whalelinter/config.json
whalelinter/dispatcher.py
whalelinter/parser.py
whalelinter/token.py
whalelinter/utils.py
whalelinter/commands/__init__.py
whalelinter/commands/apt.py
whalelinter/commands/command.py
whalelinter/commands/common.py