Metadata-Version: 1.1
Name: whale-linter
Version: 0.0.9.post1
Summary: A simple non professional Dockerfile linter
Home-page: https://github.com/jeromepin/whale-linter
Author: Jerome Pin
Author-email: jerome@jeromepin.fr
License: MIT
Download-URL: https://github.com/jeromepin/whale-linter/tarball/0.0.9-1
Keywords: docker,linter
Platform: Linux
Classifier: Development Status :: 4 - Beta
Classifier: License :: OSI Approved :: MIT License
Classifier: Natural Language :: English
Classifier: Operating System :: MacOS :: MacOS X
Classifier: Operating System :: POSIX :: Linux
Classifier: Programming Language :: Python :: 3
Classifier: Programming Language :: Python :: 3.2
Classifier: Programming Language :: Python :: 3.3
Classifier: Programming Language :: Python :: 3.4
Classifier: Programming Language :: Python :: 3.5
Classifier: Intended Audience :: System Administrators
